{
	"info": {
		"_postman_id": "acf32327-e0d5-4d60-a43c-5cf6ebee631b",
		"name": "json-database",
		"schema": "https://schema.getpostman.com/json/collection/v2.1.0/collection.json",
		"_exporter_id": "25085808"
	},
	"item": [
		{
			"name": "USER",
			"item": [
				{
					"name": "GET USER",
					"protocolProfileBehavior": {
						"disableBodyPruning": true
					},
					"request": {
						"method": "GET",
						"header": [],
						"body": {
							"mode": "raw",
							"raw": "{\"name\":\"basbas\"}",
							"options": {
								"raw": {
									"language": "json"
								}
							}
						},
						"url": {
							"raw": "http://localhost:3000/users",
							"protocol": "http",
							"host": [
								"localhost"
							],
							"port": "3000",
							"path": [
								"users"
							]
						}
					},
					"response": []
				},
				{
					"name": "GET USER BY ID",
					"protocolProfileBehavior": {
						"disableBodyPruning": true
					},
					"request": {
						"method": "GET",
						"header": [],
						"body": {
							"mode": "raw",
							"raw": "{\"title\" : \"baso aci\",\"ingredients\" : \"bakso, aci\",\"photo\" : \"3gp\",\"users_id\" : 31}",
							"options": {
								"raw": {
									"language": "json"
								}
							}
						},
						"url": {
							"raw": "http://localhost:3000/users/33",
							"protocol": "http",
							"host": [
								"localhost"
							],
							"port": "3000",
							"path": [
								"users",
								"33"
							]
						}
					},
					"response": []
				},
				{
					"name": "GET USER BY QUERY",
					"protocolProfileBehavior": {
						"disableBodyPruning": true
					},
					"request": {
						"method": "GET",
						"header": [],
						"body": {
							"mode": "raw",
							"raw": "{\"title\" : \"baso aci\",\"ingredients\" : \"bakso, aci\",\"photo\" : \"3gp\",\"users_id\" : 31}",
							"options": {
								"raw": {
									"language": "json"
								}
							}
						},
						"url": {
							"raw": "http://localhost:3000/users/query?searchBy=name&search=a&sortBy=name&sort=DESC&offset&limit=100",
							"protocol": "http",
							"host": [
								"localhost"
							],
							"port": "3000",
							"path": [
								"users",
								"query"
							],
							"query": [
								{
									"key": "searchBy",
									"value": "name"
								},
								{
									"key": "search",
									"value": "a"
								},
								{
									"key": "sortBy",
									"value": "name"
								},
								{
									"key": "sort",
									"value": "DESC"
								},
								{
									"key": "offset",
									"value": null
								},
								{
									"key": "limit",
									"value": "100"
								}
							]
						}
					},
					"response": []
				},
				{
					"name": "POST USER",
					"request": {
						"method": "POST",
						"header": [],
						"body": {
							"mode": "raw",
							"raw": "{\"name\": \"kutil\"}",
							"options": {
								"raw": {
									"language": "json"
								}
							}
						},
						"url": {
							"raw": "http://localhost:3000/users",
							"protocol": "http",
							"host": [
								"localhost"
							],
							"port": "3000",
							"path": [
								"users"
							]
						}
					},
					"response": []
				},
				{
					"name": "UPDATE USER",
					"protocolProfileBehavior": {
						"disableBodyPruning": true
					},
					"request": {
						"method": "GET",
						"header": [],
						"body": {
							"mode": "raw",
							"raw": "{\"name\": \"otan\"}",
							"options": {
								"raw": {
									"language": "json"
								}
							}
						},
						"url": {
							"raw": "http://localhost:3000/users/1",
							"protocol": "http",
							"host": [
								"localhost"
							],
							"port": "3000",
							"path": [
								"users",
								"1"
							]
						}
					},
					"response": []
				},
				{
					"name": "SOFT DELETE USER",
					"request": {
						"method": "PUT",
						"header": [],
						"body": {
							"mode": "raw",
							"raw": "{\"deleted_at\": true}",
							"options": {
								"raw": {
									"language": "json"
								}
							}
						},
						"url": {
							"raw": "http://localhost:3000/users/33/delete",
							"protocol": "http",
							"host": [
								"localhost"
							],
							"port": "3000",
							"path": [
								"users",
								"33",
								"delete"
							]
						}
					},
					"response": []
				}
			]
		},
		{
			"name": "CATEGORY",
			"item": [
				{
					"name": "GET ALL CATEGORY",
					"request": {
						"method": "GET",
						"header": [],
						"url": {
							"raw": "http://localhost:3000/category",
							"protocol": "http",
							"host": [
								"localhost"
							],
							"port": "3000",
							"path": [
								"category"
							]
						}
					},
					"response": []
				},
				{
					"name": "GET CATEGORY BY ID",
					"request": {
						"method": "GET",
						"header": [],
						"url": {
							"raw": "http://localhost:3000/category/1",
							"protocol": "http",
							"host": [
								"localhost"
							],
							"port": "3000",
							"path": [
								"category",
								"1"
							]
						}
					},
					"response": []
				},
				{
					"name": "GET CATEGORY BY QUERY",
					"protocolProfileBehavior": {
						"disableBodyPruning": true
					},
					"request": {
						"method": "GET",
						"header": [],
						"body": {
							"mode": "raw",
							"raw": "{\"title\": \"minuman dingin\"}",
							"options": {
								"raw": {
									"language": "json"
								}
							}
						},
						"url": {
							"raw": "http://localhost:3000/category/query?sortBy=title&sort=asc&offset&limit",
							"protocol": "http",
							"host": [
								"localhost"
							],
							"port": "3000",
							"path": [
								"category",
								"query"
							],
							"query": [
								{
									"key": "sortBy",
									"value": "title"
								},
								{
									"key": "sort",
									"value": "asc"
								},
								{
									"key": "offset",
									"value": null
								},
								{
									"key": "limit",
									"value": null
								}
							]
						}
					},
					"response": []
				},
				{
					"name": "POST CATEGORY",
					"request": {
						"method": "POST",
						"header": [],
						"body": {
							"mode": "raw",
							"raw": "{\"title\": \"minuman dingin\"}",
							"options": {
								"raw": {
									"language": "json"
								}
							}
						},
						"url": {
							"raw": "http://localhost:3000/category/",
							"protocol": "http",
							"host": [
								"localhost"
							],
							"port": "3000",
							"path": [
								"category",
								""
							]
						}
					},
					"response": []
				},
				{
					"name": "UPDATE CATEGORY",
					"request": {
						"method": "PUT",
						"header": [],
						"body": {
							"mode": "raw",
							"raw": "{\"title\": \"main food\"}",
							"options": {
								"raw": {
									"language": "json"
								}
							}
						},
						"url": {
							"raw": "http://localhost:3000/category/id/1",
							"protocol": "http",
							"host": [
								"localhost"
							],
							"port": "3000",
							"path": [
								"category",
								"id",
								"1"
							]
						}
					},
					"response": []
				},
				{
					"name": "SOFT DELETE CATEGORY",
					"request": {
						"method": "PUT",
						"header": [],
						"body": {
							"mode": "raw",
							"raw": "{\"title\": \"main food\"}",
							"options": {
								"raw": {
									"language": "json"
								}
							}
						},
						"url": {
							"raw": "http://localhost:3000/category/id/1",
							"protocol": "http",
							"host": [
								"localhost"
							],
							"port": "3000",
							"path": [
								"category",
								"id",
								"1"
							]
						}
					},
					"response": []
				}
			]
		},
		{
			"name": "RECIPES",
			"item": [
				{
					"name": "GET RECIPES",
					"request": {
						"method": "GET",
						"header": [],
						"url": {
							"raw": "http://localhost:3000/recipes",
							"protocol": "http",
							"host": [
								"localhost"
							],
							"port": "3000",
							"path": [
								"recipes"
							]
						}
					},
					"response": []
				},
				{
					"name": "GET RECIPE BY NAME",
					"protocolProfileBehavior": {
						"disableBodyPruning": true
					},
					"request": {
						"method": "GET",
						"header": [],
						"body": {
							"mode": "raw",
							"raw": "{\"title\" : \"baso aci\",\"ingredients\" : \"bakso, aci\",\"photo\" : \"3gp\",\"users_id\" : 31}",
							"options": {
								"raw": {
									"language": "json"
								}
							}
						},
						"url": {
							"raw": "http://localhost:3000/recipes/baso",
							"protocol": "http",
							"host": [
								"localhost"
							],
							"port": "3000",
							"path": [
								"recipes",
								"baso"
							]
						}
					},
					"response": []
				},
				{
					"name": "GET RECIPE BY ID",
					"protocolProfileBehavior": {
						"disableBodyPruning": true
					},
					"request": {
						"method": "GET",
						"header": [],
						"body": {
							"mode": "raw",
							"raw": "{\"title\" : \"baso aci\",\"ingredients\" : \"bakso, aci\",\"photo\" : \"3gp\",\"users_id\" : 31}",
							"options": {
								"raw": {
									"language": "json"
								}
							}
						},
						"url": {
							"raw": "http://localhost:3000/recipes/id/1",
							"protocol": "http",
							"host": [
								"localhost"
							],
							"port": "3000",
							"path": [
								"recipes",
								"id",
								"1"
							]
						}
					},
					"response": []
				},
				{
					"name": "GET RECIPE BY QUERY",
					"protocolProfileBehavior": {
						"disableBodyPruning": true
					},
					"request": {
						"method": "GET",
						"header": [],
						"body": {
							"mode": "raw",
							"raw": "{\"title\" : \"baso aci\",\"ingredients\" : \"bakso, aci\",\"photo\" : \"3gp\",\"users_id\" : 31}",
							"options": {
								"raw": {
									"language": "json"
								}
							}
						},
						"url": {
							"raw": "http://localhost:3000/recipes?sort=desc&search=baso&sortBy=created_at&offset=&limit=",
							"protocol": "http",
							"host": [
								"localhost"
							],
							"port": "3000",
							"path": [
								"recipes"
							],
							"query": [
								{
									"key": "sort",
									"value": "desc"
								},
								{
									"key": "search",
									"value": "baso"
								},
								{
									"key": "sortBy",
									"value": "created_at"
								},
								{
									"key": "offset",
									"value": ""
								},
								{
									"key": "limit",
									"value": ""
								}
							]
						}
					},
					"response": []
				},
				{
					"name": "POST RECIPES",
					"request": {
						"method": "POST",
						"header": [],
						"body": {
							"mode": "raw",
							"raw": "{\"title\": \"Babi Guling\", \"ingredients\": \"babi crispy\", \"photo\": \"babi.jpg\", \"users_id\": 33, \"category_id\":1}",
							"options": {
								"raw": {
									"language": "json"
								}
							}
						},
						"url": {
							"raw": "http://localhost:3000/recipes/",
							"protocol": "http",
							"host": [
								"localhost"
							],
							"port": "3000",
							"path": [
								"recipes",
								""
							]
						}
					},
					"response": []
				},
				{
					"name": "UPDATE RECIPES",
					"request": {
						"method": "PUT",
						"header": [],
						"body": {
							"mode": "raw",
							"raw": "{\"ingredients\":\"gula dan susu\"}",
							"options": {
								"raw": {
									"language": "json"
								}
							}
						},
						"url": {
							"raw": "http://localhost:3000/recipes/id/18",
							"protocol": "http",
							"host": [
								"localhost"
							],
							"port": "3000",
							"path": [
								"recipes",
								"id",
								"18"
							]
						}
					},
					"response": []
				},
				{
					"name": "SOFT DELETE RECIPES",
					"request": {
						"method": "PUT",
						"header": [],
						"body": {
							"mode": "raw",
							"raw": "{\"deleted_at\" : true}",
							"options": {
								"raw": {
									"language": "json"
								}
							}
						},
						"url": {
							"raw": "http://localhost:3000/recipes/id/19",
							"protocol": "http",
							"host": [
								"localhost"
							],
							"port": "3000",
							"path": [
								"recipes",
								"id",
								"19"
							]
						}
					},
					"response": []
				}
			]
		}
	]
}